utils/Var_Plm.py
utils/__init__.py
yifan_demo_h-0.0.2.dist-info/METADATA
yifan_demo_h-0.0.2.dist-info/WHEEL
yifan_demo_h-0.0.2.dist-info/licenses/LICENSE.txt
yifan_demo_h-0.0.2.dist-info/RECORD
